[
  {
    "id": "generic-1760285400166",
    "type": "generic",
    "data": {
      "typ": "reklamace",
      "contract": "Natuzzi Editions - Strejcek",
      "cislo": "TE|ST",
      "zakaznik": "novak",
      "adresa": "Do Dubče 35, Praha, 190 11",
      "telefon": "+420 87878787",
      "email": "seznam@seznam.cz",
      "produkt": "test",
      "datum_prodeje": "2025-10-01",
      "datum_reklamace": "2025-10-01",
      "popis": "vadí mi to už ",
      "fotky": [
        ""
      ]
    },
    "created": "2025-10-12T16:10:00.166Z",
    "updated": "2025-10-12T16:10:00.166Z"
  },
  {
    "id": "generic-1760287335566",
    "type": "generic",
    "data": {
      "typ": "reklamace",
      "contract": "Natuzzi Editions - Strejcek",
      "cislo": "LKJSF",
      "zakaznik": "aůlokjpasof",
      "adresa": "Do Dubče, Praha, 190 11",
      "telefon": "+420 alkjsafdq",
      "email": "akjksafd@alskfpa.cz",
      "produkt": "BCCC",
      "datum_prodeje": "2025-10-07",
      "datum_reklamace": "2025-10-07",
      "popis": "alkjlaksjdfasf",
      "fotky": []
    },
    "created": "2025-10-12T16:42:15.566Z",
    "updated": "2025-10-12T16:42:15.566Z"
  },
  {
    "id": "generic-1760288322641",
    "type": "generic",
    "data": [],
    "created": "2025-10-12T16:49:47.059Z",
    "updated": "2025-10-12T16:58:42.641Z"
  }
]